cr_enhanced_report/__init__.py
cr_enhanced_report/cli.py
cr_enhanced_report/commands.py
cr_enhanced_report/datatypes.py
cr_enhanced_report/db.py
cr_enhanced_report/reporter.py
cr_enhanced_report-0.0.2.dist-info/LICENSE
cr_enhanced_report-0.0.2.dist-info/METADATA
cr_enhanced_report-0.0.2.dist-info/WHEEL
cr_enhanced_report-0.0.2.dist-info/entry_points.txt
cr_enhanced_report-0.0.2.dist-info/top_level.txt
cr_enhanced_report-0.0.2.dist-info/RECORD
