Metadata-Version: 2.1
Name: cr_enhanced_report
Version: 0.0.2
Summary: Enhanced report for Cosmic-Ray.
Author-email: Peter McDonald <git@petermcdonald.co.uk>
Maintainer-email: Peter McDonald <git@petermcdonald.co.uk>
License: MIT License
Project-URL: Homepage, https://github.com/petermcd/cr_enhanced_report
Project-URL: Documentation, https://github.com/petermcd/cr_enhanced_report
Project-URL: Repository, https://github.com/petermcd/cr_enhanced_report
Project-URL: Issues, https://github.com/petermcd/cr_enhanced_report/issues
Keywords: cosmic-ray,enhanced report,mutation,plugin,testing
Classifier: Development Status :: 4 - Beta
Classifier: Intended Audience :: Developers
Classifier: Topic :: Software Development :: Bug Tracking
Classifier: Topic :: Software Development :: Testing
Classifier: License :: OSI Approved :: MIT License
Classifier: Programming Language :: Python :: 3.10
Classifier: Programming Language :: Python :: 3.11
Classifier: Programming Language :: Python :: 3.12
Requires-Python: <3.13,>=3.10
License-File: LICENSE
Requires-Dist: cosmic-ray >=8.3
Provides-Extra: build
Requires-Dist: build ; extra == 'build'
Requires-Dist: wheel ; extra == 'build'
Provides-Extra: test
Requires-Dist: cosmic-ray ; extra == 'test'
Requires-Dist: flake8 ; extra == 'test'
Requires-Dist: isort ; extra == 'test'
Requires-Dist: mypy ; extra == 'test'
Requires-Dist: pre-commit ; extra == 'test'
Requires-Dist: pytest ; extra == 'test'
Requires-Dist: pytest-cov ; extra == 'test'
Requires-Dist: pytest-mock ; extra == 'test'
